fortranman
