Metadata-Version: 1.1
Name: fortranman
Version: 0.1.0
Summary: Man pages for fortran
Home-page: https://github.com/alejandrogallo/fortranman
Author: Alejandro Gallo
Author-email: aamsgallo@gmail.com
License: GNU General Public License v3
Keywords: fortranman
Platform: UNKNOWN
Classifier: Development Status :: 2 - Pre-Alpha
Classifier: Intended Audience :: Developers
Classifier: License :: OSI Approved :: GNU General Public License v3 (GPLv3)
Classifier: Natural Language :: English
Classifier: Programming Language :: Python :: 3.4
Classifier: Programming Language :: Python :: 3.5
Classifier: Programming Language :: Python :: 3.6
